{
  "battles": [
    {
      "id": 1,
      "date": "2021-03-01",
      "maps_fk": 1
    },
    {
      "id": 2,
      "date": "2021-03-02",
      "maps_fk": 2
    },
    {
      "id": 3,
      "date": "2021-03-03",
      "maps_fk": 3
    }
  ],
  "players": [
    {
      "id": 1,
      "battles_fk": 1,
      "users_fk": 1,
      "country": "USSR",
      "team": 1,
      "result": "win",
      "score": 10000
    },
    {
      "id": 2,
      "battles_fk": 1,
      "users_fk": 2,
      "country": "Germany",
      "team": 2,
      "result": "lose",
      "score": 5000
    }
  ],
  "users": [
    {
      "id": 1,
      "nickname": "User1",
      "register_date": "2021-03-01",
      "email": "user1@hof.com"
    },
    {
      "id": 2,
      "nickname": "User2",
      "register_date": "2021-03-01",
      "email": "user2@hof.com"
    },
    {
      "id": 3,
      "nickname": "User3",
      "register_date": "2021-03-01",
      "email": "user3@hof.com"
    }
  ]
}
